EEGAnalysis/__init__.py
EEGAnalysis/__main__.py
EEGAnalysis/bout_analysis.py
EEGAnalysis/get_animal_conditions.py
EEGAnalysis/get_config.py
EEGAnalysis/output_results.py
EEGAnalysis/run_main_analysis.py
EEGAnalysis/spectral.py
eeg_sleep_analysis-1.2.10.dist-info/LICENSE.md
eeg_sleep_analysis-1.2.10.dist-info/METADATA
eeg_sleep_analysis-1.2.10.dist-info/WHEEL
eeg_sleep_analysis-1.2.10.dist-info/entry_points.txt
eeg_sleep_analysis-1.2.10.dist-info/top_level.txt
eeg_sleep_analysis-1.2.10.dist-info/RECORD
