Metadata-Version: 2.1
Name: eeg-sleep-analysis
Version: 1.2.10
Summary: Package to analyze EEG-scored sleep
Home-page: https://github.com/ijperron/EEGAnalysis
Author: Isaac J. Perron
Author-email: ijperron@gmail.com
License: UNKNOWN
Platform: UNKNOWN
Classifier: Programming Language :: Python :: 3
Classifier: License :: OSI Approved :: MIT License
Classifier: Operating System :: OS Independent
Requires-Python: >=3.6
Requires-Dist: pandas
Requires-Dist: xlsxwriter
Requires-Dist: openpyxl
Requires-Dist: PySimpleGUI
